topos_theme/__init__.py
topos_theme/layout.html
topos_theme/page.html
topos_theme/theme.conf
topos_theme/__pycache__/__init__.cpython-36.pyc
topos_theme/static/css/main.css
topos_theme-0.0.3.dist-info/METADATA
topos_theme-0.0.3.dist-info/RECORD
topos_theme-0.0.3.dist-info/WHEEL
topos_theme-0.0.3.dist-info/entry_points.txt
topos_theme-0.0.3.dist-info/top_level.txt
