Metadata-Version: 2.1
Name: topos-theme
Version: 0.0.3
Summary: Topos theme for sphinx
Home-page: https://github.com/alcarney/topos-theme
Author: Alex Carney
Author-email: alcarneyme@gmail.com
License: MIT
Platform: UNKNOWN
Classifier: Framework :: Sphinx
Classifier: Framework :: Sphinx :: Theme
Classifier: License :: OSI Approved :: MIT License
Classifier: Programming Language :: Python :: 3
Classifier: Programming Language :: Python :: 3.6
Classifier: Topic :: Documentation
Classifier: Topic :: Software Development :: Documentation
Requires-Dist: sphinx
